MANIFEST.in
README.rst
setup.py
django_pygmy/__init__.py
django_pygmy/test_settings.py
django_pygmy.egg-info/PKG-INFO
django_pygmy.egg-info/SOURCES.txt
django_pygmy.egg-info/dependency_links.txt
django_pygmy.egg-info/not-zip-safe
django_pygmy.egg-info/requires.txt
django_pygmy.egg-info/top_level.txt
django_pygmy/templatetags/__init__.py
django_pygmy/templatetags/pygmy.py
django_pygmy/tests/__init__.py
django_pygmy/tests/models.py
django_pygmy/tests/testrunner.py
django_pygmy/tests/tests.py