Metadata-Version: 1.0
Name: django-pygmy
Version: 0.1.5
Summary: UNKNOWN
Home-page: https://github.com/mattack108/django-pygmy/
Author: Matt Lenc
Author-email: matt.lenc@gmail.com
License: UNKNOWN
Platform: UNKNOWN
